AUTHORS
CHANGELOG
LICENSE
MANIFEST.in
README.md
setup.py
django_redactorjs.egg-info/PKG-INFO
django_redactorjs.egg-info/SOURCES.txt
django_redactorjs.egg-info/dependency_links.txt
django_redactorjs.egg-info/not-zip-safe
django_redactorjs.egg-info/requires.txt
django_redactorjs.egg-info/top_level.txt
redactor/__init__.py
redactor/__init__.pyc
redactor/fields.py
redactor/forms.py
redactor/forms.pyc
redactor/models.py
redactor/models.pyc
redactor/tests.py
redactor/tests.pyc
redactor/urls.py
redactor/urls.pyc
redactor/views.py
redactor/views.pyc
redactor/widgets.py
redactor/widgets.pyc
redactor/__pycache__/__init__.cpython-32.pyc
redactor/__pycache__/__init__.cpython-33.pyc
redactor/__pycache__/__init__.cpython-34.pyc
redactor/__pycache__/__init__.cpython-36.pyc
redactor/__pycache__/__init__.cpython-37.pyc
redactor/__pycache__/__init__.pypy-22.pyc
redactor/__pycache__/__init__.pypy-41.pyc
redactor/__pycache__/forms.cpython-32.pyc
redactor/__pycache__/forms.cpython-33.pyc
redactor/__pycache__/forms.cpython-34.pyc
redactor/__pycache__/forms.cpython-36.pyc
redactor/__pycache__/forms.pypy-22.pyc
redactor/__pycache__/forms.pypy-41.pyc
redactor/__pycache__/models.cpython-32.pyc
redactor/__pycache__/models.cpython-33.pyc
redactor/__pycache__/models.cpython-34.pyc
redactor/__pycache__/models.cpython-36.pyc
redactor/__pycache__/models.pypy-22.pyc
redactor/__pycache__/models.pypy-41.pyc
redactor/__pycache__/tests.cpython-32.pyc
redactor/__pycache__/tests.cpython-33.pyc
redactor/__pycache__/tests.cpython-34.pyc
redactor/__pycache__/tests.cpython-36.pyc
redactor/__pycache__/tests.pypy-22.pyc
redactor/__pycache__/tests.pypy-41.pyc
redactor/__pycache__/urls.cpython-32.pyc
redactor/__pycache__/urls.cpython-33.pyc
redactor/__pycache__/urls.cpython-34.pyc
redactor/__pycache__/urls.cpython-36.pyc
redactor/__pycache__/urls.pypy-22.pyc
redactor/__pycache__/urls.pypy-41.pyc
redactor/__pycache__/views.cpython-32.pyc
redactor/__pycache__/views.cpython-33.pyc
redactor/__pycache__/views.cpython-34.pyc
redactor/__pycache__/views.cpython-36.pyc
redactor/__pycache__/views.pypy-22.pyc
redactor/__pycache__/views.pypy-41.pyc
redactor/__pycache__/widgets.cpython-32.pyc
redactor/__pycache__/widgets.cpython-33.pyc
